kmeans_radec.py
lumfunc.py
lumfunc-1.0.0.dist-info/LICENSE
lumfunc-1.0.0.dist-info/METADATA
lumfunc-1.0.0.dist-info/WHEEL
lumfunc-1.0.0.dist-info/top_level.txt
lumfunc-1.0.0.dist-info/RECORD
