Metadata-Version: 2.1
Name: lumfunc
Version: 1.0.0
Summary: Galaxian Luminosity Function Constructor package using the 1/Vmax estimator and Schechter model.
Home-page: https://github.com/manasveesaraf/LuminosityFunction
Author: Manasvee Saraf
Author-email: saraf.manasvee@gmail.com
License: UNKNOWN
Platform: UNKNOWN
Classifier: Programming Language :: Python :: 3
Classifier: License :: OSI Approved :: MIT License
Classifier: Operating System :: OS Independent
Requires-Dist: scipy
Requires-Dist: matplotlib
Requires-Dist: numpy
Requires-Dist: astropy
